BVTtestbhvipparla/__init__.py
BVTtestbhvipparla/unique_key.py
BVTtestbhvipparla-0.1.1.dist-info/METADATA
BVTtestbhvipparla-0.1.1.dist-info/WHEEL
BVTtestbhvipparla-0.1.1.dist-info/top_level.txt
BVTtestbhvipparla-0.1.1.dist-info/RECORD
