Metadata-Version: 2.1
Name: BVTtestbhvipparla
Version: 0.1.1
Summary: A package to validate unique keys in Spark DataFrames
Author: Bhanu Krishna Prasad
Author-email: bhanuk@maqsoftware.com
Classifier: Programming Language :: Python :: 3
Classifier: License :: OSI Approved :: MIT License
Classifier: Operating System :: OS Independent
Requires-Python: >=3.1
Requires-Dist: pyspark
